{"results": [{"source": {"page": "lawyers.law.cornell.edu/lawyers/bankruptcy/michigan/taylor", "subdomain": "lawyers.law.cornell.edu", "root_domain": "cornell.edu", "title": "", "last_crawled": "2024-07-08", "http_code": 15, "pages_to_page": 16, "nofollow_pages_to_page": 7, "redirect_pages_to_page": 1, "external_pages_to_page": 8, "external_nofollow_pages_to_page": 7, "external_redirect_pages_to_page": 0, "deleted_pages_to_page": 18, "root_domains_to_page": 7, "indirect_root_domains_to_page": 0, "deleted_root_domains_to_page": 8, "nofollow_root_domains_to_page": 6, "pages_to_subdomain": 27499010, "nofollow_pages_to_subdomain": 449267, "redirect_pages_to_subdomain": 341869, "external_pages_to_subdomain": 312878, "external_nofollow_pages_to_subdomain": 158605, "external_redirect_pages_to_subdomain": 1163, "deleted_pages_to_subdomain": 68111, "root_domains_to_subdomain": 5157, "deleted_root_domains_to_subdomain": 975, "nofollow_root_domains_to_subdomain": 1102, "pages_to_root_domain": 641128364, "nofollow_pages_to_root_domain": 119786295, "redirect_pages_to_root_domain": 2512780, "external_pages_to_root_domain": 133845561, "external_indirect_pages_to_root_domain": 34375013, "external_nofollow_pages_to_root_domain": 8514057, "external_redirect_pages_to_root_domain": 833276, "deleted_pages_to_root_domain": 98789843, "root_domains_to_root_domain": 500144, "indirect_root_domains_to_root_domain": 7100, "deleted_root_domains_to_root_domain": 70609, "nofollow_root_domains_to_root_domain": 73992, "page_authority": 51, "domain_authority": 93, "link_propensity": 0.01370099094, "spam_score": 1, "root_domains_from_page": 18, "nofollow_root_domains_from_page": 2, "pages_from_page": 50, "nofollow_pages_from_page": 4, "root_domains_from_root_domain": 190307, "nofollow_root_domains_from_root_domain": 54872, "pages_from_root_domain": 3826813, "nofollow_pages_from_root_domain": 130103, "pages_crawled_from_root_domain": 13890017}, "target": {"page": "bermanbishoplaw.com/", "subdomain": "bermanbishoplaw.com", "root_domain": "bermanbishoplaw.com", "title": "", "last_crawled": "2024-04-08", "http_code": 403, "pages_to_page": 1061, "nofollow_pages_to_page": 551, "redirect_pages_to_page": 7, "external_pages_to_page": 1057, "external_nofollow_pages_to_page": 551, "external_redirect_pages_to_page": 7, "deleted_pages_to_page": 748, "root_domains_to_page": 71, "indirect_root_domains_to_page": 4, "deleted_root_domains_to_page": 77, "nofollow_root_domains_to_page": 45, "pages_to_subdomain": 1368, "nofollow_pages_to_subdomain": 668, "redirect_pages_to_subdomain": 174, "external_pages_to_subdomain": 1207, "external_nofollow_pages_to_subdomain": 668, "external_redirect_pages_to_subdomain": 35, "deleted_pages_to_subdomain": 2734, "root_domains_to_subdomain": 95, "deleted_root_domains_to_subdomain": 72, "nofollow_root_domains_to_subdomain": 62, "pages_to_root_domain": 2030, "nofollow_pages_to_root_domain": 1115, "redirect_pages_to_root_domain": 331, "external_pages_to_root_domain": 1869, "external_indirect_pages_to_root_domain": 123, "external_nofollow_pages_to_root_domain": 1115, "external_redirect_pages_to_root_domain": 192, "deleted_pages_to_root_domain": 2773, "root_domains_to_root_domain": 185, "indirect_root_domains_to_root_domain": 32, "deleted_root_domains_to_root_domain": 29, "nofollow_root_domains_to_root_domain": 90, "page_authority": 31, "domain_authority": 17, "link_propensity": 0.001023017918, "spam_score": 1, "root_domains_from_page": 0, "nofollow_root_domains_from_page": 0, "pages_from_page": 0, "nofollow_pages_from_page": 0, "root_domains_from_root_domain": 4, "nofollow_root_domains_from_root_domain": 0, "pages_from_root_domain": 4, "nofollow_pages_from_root_domain": 0, "pages_crawled_from_root_domain": 3910}, "anchor_text": "view website", "date_first_seen": "2021-06-03", "date_last_seen": "2022-03-14", "date_disappeared": "2021-06-07", "nofollow": false, "redirect": false, "rel_canonical": false, "via_redirect": false, "via_rel_canonical": false}], "next_token": "ATfqmzXtpI3/"}
