{"results": [{"source": {"page": "slashdot.org/submission/12068513/cooking-with-cbd-oil", "subdomain": "slashdot.org", "root_domain": "slashdot.org", "title": "", "last_crawled": "2024-06-29", "http_code": 5, "pages_to_page": 4, "nofollow_pages_to_page": 0, "redirect_pages_to_page": 0, "external_pages_to_page": 3, "external_nofollow_pages_to_page": 0, "external_redirect_pages_to_page": 0, "deleted_pages_to_page": 0, "root_domains_to_page": 3, "indirect_root_domains_to_page": 0, "deleted_root_domains_to_page": 0, "nofollow_root_domains_to_page": 0, "pages_to_subdomain": 299951415, "nofollow_pages_to_subdomain": 52541398, "redirect_pages_to_subdomain": 983687, "external_pages_to_subdomain": 31859321, "external_nofollow_pages_to_subdomain": 7958669, "external_redirect_pages_to_subdomain": 42172, "deleted_pages_to_subdomain": 37143288, "root_domains_to_subdomain": 159457, "deleted_root_domains_to_subdomain": 25547, "nofollow_root_domains_to_subdomain": 42085, "pages_to_root_domain": 438116501, "nofollow_pages_to_root_domain": 55420819, "redirect_pages_to_root_domain": 1237952, "external_pages_to_root_domain": 102440266, "external_indirect_pages_to_root_domain": 33748717, "external_nofollow_pages_to_root_domain": 10092973, "external_redirect_pages_to_root_domain": 107588, "deleted_pages_to_root_domain": 47483515, "root_domains_to_root_domain": 229570, "indirect_root_domains_to_root_domain": 2081, "deleted_root_domains_to_root_domain": 32078, "nofollow_root_domains_to_root_domain": 51307, "page_authority": 46, "domain_authority": 91, "link_propensity": 0.0482455343, "spam_score": 1, "root_domains_from_page": 9, "nofollow_root_domains_from_page": 9, "pages_from_page": 13, "nofollow_pages_from_page": 13, "root_domains_from_root_domain": 442007, "nofollow_root_domains_from_root_domain": 251367, "pages_from_root_domain": 8794432, "nofollow_pages_from_root_domain": 6960074, "pages_crawled_from_root_domain": 9161615}, "target": {"page": "evo3oliveoil.com/", "subdomain": "evo3oliveoil.com", "root_domain": "evo3oliveoil.com", "title": "Extra Virgin Olive Oil - 100% Organic - EVO3 Olive Oil", "last_crawled": "2024-07-05", "http_code": 200, "pages_to_page": 211, "nofollow_pages_to_page": 46, "redirect_pages_to_page": 5, "external_pages_to_page": 185, "external_nofollow_pages_to_page": 46, "external_redirect_pages_to_page": 4, "deleted_pages_to_page": 82, "root_domains_to_page": 93, "indirect_root_domains_to_page": 24, "deleted_root_domains_to_page": 20, "nofollow_root_domains_to_page": 22, "pages_to_subdomain": 744, "nofollow_pages_to_subdomain": 83, "redirect_pages_to_subdomain": 31, "external_pages_to_subdomain": 253, "external_nofollow_pages_to_subdomain": 66, "external_redirect_pages_to_subdomain": 5, "deleted_pages_to_subdomain": 137, "root_domains_to_subdomain": 116, "deleted_root_domains_to_subdomain": 36, "nofollow_root_domains_to_subdomain": 33, "pages_to_root_domain": 765, "nofollow_pages_to_root_domain": 84, "redirect_pages_to_root_domain": 31, "external_pages_to_root_domain": 272, "external_indirect_pages_to_root_domain": 47, "external_nofollow_pages_to_root_domain": 67, "external_redirect_pages_to_root_domain": 5, "deleted_pages_to_root_domain": 143, "root_domains_to_root_domain": 116, "indirect_root_domains_to_root_domain": 15, "deleted_root_domains_to_root_domain": 36, "nofollow_root_domains_to_root_domain": 33, "page_authority": 30, "domain_authority": 25, "link_propensity": 0.05168985948, "spam_score": 1, "root_domains_from_page": 5, "nofollow_root_domains_from_page": 4, "pages_from_page": 6, "nofollow_pages_from_page": 5, "root_domains_from_root_domain": 26, "nofollow_root_domains_from_root_domain": 4, "pages_from_root_domain": 43, "nofollow_pages_from_root_domain": 5, "pages_crawled_from_root_domain": 503}, "anchor_text": "(evo3oliveoil.com)", "date_first_seen": "2021-06-16", "date_last_seen": "2021-11-04", "date_disappeared": "", "nofollow": true, "redirect": false, "rel_canonical": false, "via_redirect": false, "via_rel_canonical": false}], "next_token": "ASYQXE1n9hpn"}
