{"results": [{"source": {"page": "cgi.www5a.biglobe.ne.jp/%7Et-masa/g_book.cgi/RK=0/RS=kaEu3FOWW3BvYMqz_5Iplo9vt24-?g2_returnName=Album", "subdomain": "cgi.www5a.biglobe.ne.jp", "root_domain": "biglobe.ne.jp", "title": "\ufffd\ufffd\ufffd\ufffd\ufffd\u0181E\ufffd\u0502\ufffd\ufffd\ufffd", "last_crawled": "2024-05-14", "http_code": 200, "pages_to_page": 46, "nofollow_pages_to_page": 38, "redirect_pages_to_page": 0, "external_pages_to_page": 46, "external_nofollow_pages_to_page": 38, "external_redirect_pages_to_page": 0, "deleted_pages_to_page": 104, "root_domains_to_page": 11, "indirect_root_domains_to_page": 0, "deleted_root_domains_to_page": 7, "nofollow_root_domains_to_page": 8, "pages_to_subdomain": 718159, "nofollow_pages_to_subdomain": 127368, "redirect_pages_to_subdomain": 278, "external_pages_to_subdomain": 436661, "external_nofollow_pages_to_subdomain": 127368, "external_redirect_pages_to_subdomain": 248, "deleted_pages_to_subdomain": 172223, "root_domains_to_subdomain": 13776, "deleted_root_domains_to_subdomain": 3811, "nofollow_root_domains_to_subdomain": 5948, "pages_to_root_domain": 1319108108, "nofollow_pages_to_root_domain": 37509420, "redirect_pages_to_root_domain": 13998446, "external_pages_to_root_domain": 129974765, "external_indirect_pages_to_root_domain": 34179031, "external_nofollow_pages_to_root_domain": 12606433, "external_redirect_pages_to_root_domain": 11752083, "deleted_pages_to_root_domain": 1171596326, "root_domains_to_root_domain": 284388, "indirect_root_domains_to_root_domain": 52714, "deleted_root_domains_to_root_domain": 29935, "nofollow_root_domains_to_root_domain": 48940, "page_authority": 50, "domain_authority": 91, "link_propensity": 0.02686978132, "spam_score": 17, "root_domains_from_page": 9, "nofollow_root_domains_from_page": 0, "pages_from_page": 9, "nofollow_pages_from_page": 0, "root_domains_from_root_domain": 672188, "nofollow_root_domains_from_root_domain": 3957, "pages_from_root_domain": 16185318, "nofollow_pages_from_root_domain": 5046863, "pages_crawled_from_root_domain": 25016504}, "target": {"page": "sildenafilx5.online/", "subdomain": "sildenafilx5.online", "root_domain": "sildenafilx5.online", "title": "", "last_crawled": "2024-05-26", "http_code": 15, "pages_to_page": 1432, "nofollow_pages_to_page": 1081, "redirect_pages_to_page": 0, "external_pages_to_page": 1432, "external_nofollow_pages_to_page": 1081, "external_redirect_pages_to_page": 0, "deleted_pages_to_page": 1150, "root_domains_to_page": 271, "indirect_root_domains_to_page": 0, "deleted_root_domains_to_page": 90, "nofollow_root_domains_to_page": 185, "pages_to_subdomain": 1437, "nofollow_pages_to_subdomain": 1081, "redirect_pages_to_subdomain": 0, "external_pages_to_subdomain": 1437, "external_nofollow_pages_to_subdomain": 1081, "external_redirect_pages_to_subdomain": 0, "deleted_pages_to_subdomain": 1161, "root_domains_to_subdomain": 271, "deleted_root_domains_to_subdomain": 92, "nofollow_root_domains_to_subdomain": 185, "pages_to_root_domain": 1478, "nofollow_pages_to_root_domain": 1083, "redirect_pages_to_root_domain": 0, "external_pages_to_root_domain": 1478, "external_indirect_pages_to_root_domain": 0, "external_nofollow_pages_to_root_domain": 1083, "external_redirect_pages_to_root_domain": 0, "deleted_pages_to_root_domain": 1163, "root_domains_to_root_domain": 284, "indirect_root_domains_to_root_domain": 0, "deleted_root_domains_to_root_domain": 93, "nofollow_root_domains_to_root_domain": 187, "page_authority": 38, "domain_authority": 11, "link_propensity": 0, "spam_score": -1, "root_domains_from_page": 0, "nofollow_root_domains_from_page": 0, "pages_from_page": 0, "nofollow_pages_from_page": 0, "root_domains_from_root_domain": 0, "nofollow_root_domains_from_root_domain": 0, "pages_from_root_domain": 0, "nofollow_pages_from_root_domain": 0, "pages_crawled_from_root_domain": 9}, "anchor_text": "http://sildenafilx5.online", "date_first_seen": "2024-02-13", "date_last_seen": "2024-02-13", "date_disappeared": "2024-05-14", "nofollow": false, "redirect": false, "rel_canonical": false, "via_redirect": false, "via_rel_canonical": false}], "next_token": "AeA7JBre0pcx"}
