{"results": [{"source": {"page": "www.angelfire.com/in3/hifijohn/links.html", "subdomain": "www.angelfire.com", "root_domain": "www.angelfire.com", "title": "HIFIJOHN'S LINKS PAGE", "last_crawled": "2024-07-12", "http_code": 200, "pages_to_page": 28, "nofollow_pages_to_page": 25, "redirect_pages_to_page": 1, "external_pages_to_page": 26, "external_nofollow_pages_to_page": 25, "external_redirect_pages_to_page": 1, "deleted_pages_to_page": 5, "root_domains_to_page": 2, "indirect_root_domains_to_page": 0, "deleted_root_domains_to_page": 0, "nofollow_root_domains_to_page": 1, "pages_to_subdomain": 76414160, "nofollow_pages_to_subdomain": 2732969, "redirect_pages_to_subdomain": 479222, "external_pages_to_subdomain": 50462446, "external_nofollow_pages_to_subdomain": 2680161, "external_redirect_pages_to_subdomain": 372657, "deleted_pages_to_subdomain": 6242135, "root_domains_to_subdomain": 276659, "deleted_root_domains_to_subdomain": 31843, "nofollow_root_domains_to_subdomain": 37266, "pages_to_root_domain": 76414724, "nofollow_pages_to_root_domain": 2733391, "redirect_pages_to_root_domain": 479223, "external_pages_to_root_domain": 50462936, "external_indirect_pages_to_root_domain": 7032264, "external_nofollow_pages_to_root_domain": 2680583, "external_redirect_pages_to_root_domain": 372657, "deleted_pages_to_root_domain": 6242140, "root_domains_to_root_domain": 276661, "indirect_root_domains_to_root_domain": 7537, "deleted_root_domains_to_root_domain": 31843, "nofollow_root_domains_to_root_domain": 37267, "page_authority": 46, "domain_authority": 91, "link_propensity": 0.2750022113, "spam_score": -1, "root_domains_from_page": 848, "nofollow_root_domains_from_page": 0, "pages_from_page": 1239, "nofollow_pages_from_page": 0, "root_domains_from_root_domain": 1308015, "nofollow_root_domains_from_root_domain": 5114, "pages_from_root_domain": 7264100, "nofollow_pages_from_root_domain": 67636, "pages_crawled_from_root_domain": 4756380}, "target": {"page": "flatpick.com/", "subdomain": "flatpick.com", "root_domain": "flatpick.com", "title": "", "last_crawled": "2024-08-06", "http_code": 301, "pages_to_page": 257, "nofollow_pages_to_page": 173, "redirect_pages_to_page": 0, "external_pages_to_page": 257, "external_nofollow_pages_to_page": 173, "external_redirect_pages_to_page": 0, "deleted_pages_to_page": 41, "root_domains_to_page": 136, "indirect_root_domains_to_page": 0, "deleted_root_domains_to_page": 22, "nofollow_root_domains_to_page": 103, "pages_to_subdomain": 622, "nofollow_pages_to_subdomain": 229, "redirect_pages_to_subdomain": 0, "external_pages_to_subdomain": 614, "external_nofollow_pages_to_subdomain": 229, "external_redirect_pages_to_subdomain": 0, "deleted_pages_to_subdomain": 162, "root_domains_to_subdomain": 261, "deleted_root_domains_to_subdomain": 77, "nofollow_root_domains_to_subdomain": 111, "pages_to_root_domain": 172175, "nofollow_pages_to_root_domain": 1721, "redirect_pages_to_root_domain": 387, "external_pages_to_root_domain": 162636, "external_indirect_pages_to_root_domain": 152319, "external_nofollow_pages_to_root_domain": 1721, "external_redirect_pages_to_root_domain": 253, "deleted_pages_to_root_domain": 26172, "root_domains_to_root_domain": 1822, "indirect_root_domains_to_root_domain": 64, "deleted_root_domains_to_root_domain": 542, "nofollow_root_domains_to_root_domain": 417, "page_authority": 42, "domain_authority": 36, "link_propensity": 0.003689129371, "spam_score": 8, "root_domains_from_page": 0, "nofollow_root_domains_from_page": 0, "pages_from_page": 0, "nofollow_pages_from_page": 0, "root_domains_from_root_domain": 15, "nofollow_root_domains_from_root_domain": 0, "pages_from_root_domain": 215, "nofollow_pages_from_root_domain": 1, "pages_crawled_from_root_domain": 4066}, "anchor_text": "flatpick", "date_first_seen": "2016-07-06", "date_last_seen": "2024-07-12", "date_disappeared": "", "nofollow": false, "redirect": false, "rel_canonical": false, "via_redirect": false, "via_rel_canonical": false}], "next_token": "ATXcPkwygomu"}
