{"results": [{"source": {"page": "xploredomains.com/2023-12-14?page=51", "subdomain": "xploredomains.com", "root_domain": "xploredomains.com", "title": "December 14, 2023 - Page 51 | XploreDomains", "last_crawled": "2024-05-28", "http_code": 200, "pages_to_page": 7, "nofollow_pages_to_page": 0, "redirect_pages_to_page": 0, "external_pages_to_page": 0, "external_nofollow_pages_to_page": 0, "external_redirect_pages_to_page": 0, "deleted_pages_to_page": 0, "root_domains_to_page": 0, "indirect_root_domains_to_page": 0, "deleted_root_domains_to_page": 0, "nofollow_root_domains_to_page": 0, "pages_to_subdomain": 1461501, "nofollow_pages_to_subdomain": 1513, "redirect_pages_to_subdomain": 2, "external_pages_to_subdomain": 7277, "external_nofollow_pages_to_subdomain": 1511, "external_redirect_pages_to_subdomain": 1, "deleted_pages_to_subdomain": 25752, "root_domains_to_subdomain": 647, "deleted_root_domains_to_subdomain": 178, "nofollow_root_domains_to_subdomain": 277, "pages_to_root_domain": 2698172, "nofollow_pages_to_root_domain": 2833, "redirect_pages_to_root_domain": 4, "external_pages_to_root_domain": 24058, "external_indirect_pages_to_root_domain": 62, "external_nofollow_pages_to_root_domain": 2831, "external_redirect_pages_to_root_domain": 2, "deleted_pages_to_root_domain": 66730, "root_domains_to_root_domain": 1170, "indirect_root_domains_to_root_domain": 0, "deleted_root_domains_to_root_domain": 346, "nofollow_root_domains_to_root_domain": 527, "page_authority": 24, "domain_authority": 9, "link_propensity": 492.0191345, "spam_score": 2, "root_domains_from_page": 1059, "nofollow_root_domains_from_page": 1059, "pages_from_page": 1189, "nofollow_pages_from_page": 1189, "root_domains_from_root_domain": 56383423, "nofollow_root_domains_from_root_domain": 56383271, "pages_from_root_domain": 64795345, "nofollow_pages_from_root_domain": 64795171, "pages_crawled_from_root_domain": 114596}, "target": {"page": "spnng.com/", "subdomain": "spnng.com", "root_domain": "spnng.com", "title": "", "last_crawled": "2024-04-13", "http_code": 5, "pages_to_page": 9, "nofollow_pages_to_page": 5, "redirect_pages_to_page": 0, "external_pages_to_page": 9, "external_nofollow_pages_to_page": 5, "external_redirect_pages_to_page": 0, "deleted_pages_to_page": 2, "root_domains_to_page": 8, "indirect_root_domains_to_page": 0, "deleted_root_domains_to_page": 1, "nofollow_root_domains_to_page": 4, "pages_to_subdomain": 10, "nofollow_pages_to_subdomain": 5, "redirect_pages_to_subdomain": 0, "external_pages_to_subdomain": 10, "external_nofollow_pages_to_subdomain": 5, "external_redirect_pages_to_subdomain": 0, "deleted_pages_to_subdomain": 2, "root_domains_to_subdomain": 9, "deleted_root_domains_to_subdomain": 1, "nofollow_root_domains_to_subdomain": 4, "pages_to_root_domain": 10, "nofollow_pages_to_root_domain": 5, "redirect_pages_to_root_domain": 0, "external_pages_to_root_domain": 10, "external_indirect_pages_to_root_domain": 0, "external_nofollow_pages_to_root_domain": 5, "external_redirect_pages_to_root_domain": 0, "deleted_pages_to_root_domain": 2, "root_domains_to_root_domain": 9, "indirect_root_domains_to_root_domain": 0, "deleted_root_domains_to_root_domain": 1, "nofollow_root_domains_to_root_domain": 4, "page_authority": 15, "domain_authority": 2, "link_propensity": 0.3333333433, "spam_score": -1, "root_domains_from_page": 1, "nofollow_root_domains_from_page": 0, "pages_from_page": 1, "nofollow_pages_from_page": 0, "root_domains_from_root_domain": 1, "nofollow_root_domains_from_root_domain": 0, "pages_from_root_domain": 3, "nofollow_pages_from_root_domain": 0, "pages_crawled_from_root_domain": 3}, "anchor_text": "spnng.com", "date_first_seen": "2024-05-25", "date_last_seen": "2024-05-28", "date_disappeared": "", "nofollow": true, "redirect": false, "rel_canonical": false, "via_redirect": false, "via_rel_canonical": false}], "next_token": "AafxVXdWDOPp"}
