{"results": [{"source": {"page": "www.folkd.com/tag/loan-against-property-lowest-interest-rates", "subdomain": "www.folkd.com", "root_domain": "folkd.com", "title": "", "last_crawled": "2023-09-23", "http_code": 307, "pages_to_page": 1, "nofollow_pages_to_page": 0, "redirect_pages_to_page": 0, "external_pages_to_page": 0, "external_nofollow_pages_to_page": 0, "external_redirect_pages_to_page": 0, "deleted_pages_to_page": 19, "root_domains_to_page": 0, "indirect_root_domains_to_page": 0, "deleted_root_domains_to_page": 0, "nofollow_root_domains_to_page": 0, "pages_to_subdomain": 183328835, "nofollow_pages_to_subdomain": 66107820, "redirect_pages_to_subdomain": 828195, "external_pages_to_subdomain": 42193592, "external_nofollow_pages_to_subdomain": 24808166, "external_redirect_pages_to_subdomain": 13969, "deleted_pages_to_subdomain": 279836394, "root_domains_to_subdomain": 100916, "deleted_root_domains_to_subdomain": 19026, "nofollow_root_domains_to_subdomain": 35914, "pages_to_root_domain": 213345002, "nofollow_pages_to_root_domain": 79516110, "redirect_pages_to_root_domain": 5823119, "external_pages_to_root_domain": 63386250, "external_indirect_pages_to_root_domain": 19647679, "external_nofollow_pages_to_root_domain": 36960696, "external_redirect_pages_to_root_domain": 24418, "deleted_pages_to_root_domain": 305878773, "root_domains_to_root_domain": 125112, "indirect_root_domains_to_root_domain": 651, "deleted_root_domains_to_root_domain": 23776, "nofollow_root_domains_to_root_domain": 42111, "page_authority": 39, "domain_authority": 79, "link_propensity": 0.1139430255, "spam_score": 28, "root_domains_from_page": 0, "nofollow_root_domains_from_page": 0, "pages_from_page": 0, "nofollow_pages_from_page": 0, "root_domains_from_root_domain": 1345098, "nofollow_root_domains_from_root_domain": 889728, "pages_from_root_domain": 7168093, "nofollow_pages_from_root_domain": 5003050, "pages_crawled_from_root_domain": 11805005}, "target": {"page": "apnarupee.com/loan-against-property.html", "subdomain": "apnarupee.com", "root_domain": "apnarupee.com", "title": "Instant Loan Against Property in Pune | Get Low Interest Rate at Apnarupee", "last_crawled": "2024-07-22", "http_code": 200, "pages_to_page": 88, "nofollow_pages_to_page": 25, "redirect_pages_to_page": 1, "external_pages_to_page": 26, "external_nofollow_pages_to_page": 25, "external_redirect_pages_to_page": 1, "deleted_pages_to_page": 5, "root_domains_to_page": 3, "indirect_root_domains_to_page": 0, "deleted_root_domains_to_page": 1, "nofollow_root_domains_to_page": 2, "pages_to_subdomain": 1949, "nofollow_pages_to_subdomain": 183, "redirect_pages_to_subdomain": 26, "external_pages_to_subdomain": 254, "external_nofollow_pages_to_subdomain": 183, "external_redirect_pages_to_subdomain": 3, "deleted_pages_to_subdomain": 195, "root_domains_to_subdomain": 48, "deleted_root_domains_to_subdomain": 14, "nofollow_root_domains_to_subdomain": 18, "pages_to_root_domain": 5252, "nofollow_pages_to_root_domain": 392, "redirect_pages_to_root_domain": 54, "external_pages_to_root_domain": 620, "external_indirect_pages_to_root_domain": 257, "external_nofollow_pages_to_root_domain": 392, "external_redirect_pages_to_root_domain": 8, "deleted_pages_to_root_domain": 430, "root_domains_to_root_domain": 101, "indirect_root_domains_to_root_domain": 2, "deleted_root_domains_to_root_domain": 34, "nofollow_root_domains_to_root_domain": 45, "page_authority": 20, "domain_authority": 17, "link_propensity": 0.1618257314, "spam_score": 1, "root_domains_from_page": 0, "nofollow_root_domains_from_page": 0, "pages_from_page": 0, "nofollow_pages_from_page": 0, "root_domains_from_root_domain": 39, "nofollow_root_domains_from_root_domain": 0, "pages_from_root_domain": 54, "nofollow_pages_from_root_domain": 0, "pages_crawled_from_root_domain": 241}, "anchor_text": "instant loan in pune loan against property", "date_first_seen": "2020-05-28", "date_last_seen": "2023-06-04", "date_disappeared": "2023-09-23", "nofollow": true, "redirect": false, "rel_canonical": false, "via_redirect": false, "via_rel_canonical": false}], "next_token": "Aa1Xh97nbQJB"}
