{"results": [{"verdicts": {"score": 100, "malicious": true, "urlscan": {"malicious": true}, "categories": ["phishing"], "hasVerdicts": true}, "submitter": {"country": "us"}, "dom": {"size": 79733, "hash": "22fd80a7d1588768b3d5c2b4d7d86e06233540c0795b9644bfea03b3416d0b49"}, "frames": {"length": 1}, "usertags": [], "canonical": {"task": {"url": "zapatillassupraespanaprecio.com/ni%C3%A3%C2%B1os-c-15.html"}, "page": {"url": "zapatillassupraespanaprecio.com/ni%C3%A3%C2%B1os-c-15.html"}}, "task": {"visibility": "public", "method": "api", "domain": "www.zapatillassupraespanaprecio.com", "apexDomain": "zapatillassupraespanaprecio.com", "time": "2024-07-02T11:26:37.515Z", "uuid": "78ee7c33-09c2-4d5d-9442-5102a46571a9", "url": "http://www.zapatillassupraespanaprecio.com/ni%C3%A3%C2%B1os-c-15.html"}, "stats": {"uniqIPs": 1, "uniqCountries": 1, "dataLength": 2155688, "encodedDataLength": 2176019, "requests": 83}, "meta": [], "scanner": {"country": "fr"}, "links": {"length": 5}, "page": {"country": "FR", "server": "Apache", "redirected": "https-only", "ip": "196.196.38.16", "mimeType": "text/html", "title": "Zapatillas Supra Ni\u00f1os Oferta - Venta De Zapatillas Supra Espa\u00f1a", "url": "https://www.zapatillassupraespanaprecio.com/ni%C3%A3%C2%B1os-c-15.html", "tlsValidDays": 89, "tlsAgeDays": 3, "tlsValidFrom": "2024-06-29T09:56:53.000Z", "domain": "www.zapatillassupraespanaprecio.com", "apexDomain": "zapatillassupraespanaprecio.com", "asnname": "PACKETEXCHANGE, GB", "asn": "AS58065", "tlsIssuer": "R10", "status": "200"}, "text": {"size": 7873, "hash": "95b5810e5cfd7aa5e316f8a3b131582e0036595095b3431ae30a1a0713d2910d"}, "brand": [{"country": ["us"], "name": "Fake Shop", "vertical": ["Fashion"], "key": "fakeshop"}], "_id": "78ee7c33-09c2-4d5d-9442-5102a46571a9", "_score": null, "sort": [1719919597515, "78ee7c33-09c2-4d5d-9442-5102a46571a9"], "result": "https://urlscan.io/api/v1/result/78ee7c33-09c2-4d5d-9442-5102a46571a9/", "screenshot": "https://urlscan.io/screenshots/78ee7c33-09c2-4d5d-9442-5102a46571a9.png"}], "total": 89, "took": 155, "has_more": false}
