{"results": [{"verdicts": {"score": 100, "malicious": true, "urlscan": {"malicious": true}, "categories": ["phishing"], "hasVerdicts": true}, "submitter": {"country": "us"}, "dom": {"size": 33075, "hash": "db131d9119986a2d3a137f8c4f8f01d2627a8873be27afdb1060e40c63c08884"}, "frames": {"length": 2}, "usertags": [], "canonical": {"task": {"url": "jazhagun.com/index.html"}, "page": {"url": "jazhagun.com/index.html"}}, "task": {"visibility": "public", "method": "api", "domain": "jazhagun.com", "apexDomain": "jazhagun.com", "time": "2024-07-02T10:17:24.849Z", "uuid": "ac86a56f-d43c-431a-ba06-2020fd368940", "url": "https://jazhagun.com/index.html"}, "stats": {"uniqIPs": 5, "uniqCountries": 4, "dataLength": 1438923, "encodedDataLength": 1199790, "requests": 69}, "meta": [], "scanner": {"country": "de"}, "links": {"length": 11}, "page": {"country": "HK", "server": "nginx", "ip": "154.86.194.4", "mimeType": "text/html", "title": "imToken_imToken\u94b1\u5305_\u4e0b\u8f7d\u5b89\u88c5imtoken\u94b1\u5305\u5b89\u5353\u7248\u00b7(\u4e2d\u56fd)\u5b98\u65b9\u7f51\u7ad9", "url": "https://jazhagun.com/index.html", "tlsValidDays": 89, "tlsAgeDays": 5, "tlsValidFrom": "2024-06-26T15:13:09.000Z", "domain": "jazhagun.com", "apexDomain": "jazhagun.com", "asnname": "SH2206-AP UNIT A17,9F SILVERCORP INTL TOWER 707-713 NATHAN RD, HK", "asn": "AS134175", "tlsIssuer": "R11", "status": "200"}, "text": {"size": 6679, "hash": "1ac7bee0ae5e8460f9d85fc2a8b63877f55823e8f319489434704efe16da0c26"}, "brand": [{"country": ["sg"], "name": "imToken", "vertical": ["Crypto"], "key": "imtoken"}], "_id": "ac86a56f-d43c-431a-ba06-2020fd368940", "_score": null, "sort": [1719915444849, "ac86a56f-d43c-431a-ba06-2020fd368940"], "result": "https://urlscan.io/api/v1/result/ac86a56f-d43c-431a-ba06-2020fd368940/", "screenshot": "https://urlscan.io/screenshots/ac86a56f-d43c-431a-ba06-2020fd368940.png"}], "total": 5, "took": 26, "has_more": false}
