{"results": [{"verdicts": {"score": 100, "malicious": true, "urlscan": {"malicious": true}, "categories": ["phishing"], "hasVerdicts": true}, "submitter": {"country": "us"}, "dom": {"size": 87286, "hash": "e2889292dd0b907b9102ed65c34cfd080e2058d06cee742c253d799712dd3cd0"}, "frames": {"length": 1}, "usertags": [], "canonical": {"task": {"url": "onrunningcloudca.com/collections/shoes-tennis-shoes-c-1_8.html"}, "page": {"url": "onrunningcloudca.com/collections/shoes-tennis-shoes-c-1_8.html"}}, "labels": ["content.login"], "task": {"visibility": "public", "method": "api", "domain": "onrunningcloudca.com", "apexDomain": "onrunningcloudca.com", "time": "2024-07-02T09:19:41.637Z", "uuid": "72f450ac-153d-472c-a280-642fd5787eed", "url": "http://onrunningcloudca.com/collections/shoes-tennis-shoes-c-1_8.html?&size=7.5&gender=1"}, "stats": {"uniqIPs": 3, "uniqCountries": 2, "dataLength": 1675207, "encodedDataLength": 1689213, "requests": 47}, "meta": [], "scanner": {"country": "de"}, "links": {"length": 5}, "page": {"country": "EE", "server": "Apache", "redirected": "sub-domain", "ip": "165.231.190.149", "mimeType": "text/html", "title": "On Running Mens Tennis Shoes 7.5 Outlet Canada - On Running Cheap Online", "url": "https://www.onrunningcloudca.com/collections/shoes-tennis-shoes-c-1_8.html?&size=7.5&gender=1", "tlsValidDays": 89, "tlsAgeDays": 0, "tlsValidFrom": "2024-07-02T03:03:36.000Z", "domain": "www.onrunningcloudca.com", "apexDomain": "onrunningcloudca.com", "asnname": "PACKETEXCHANGE, GB", "asn": "AS58065", "tlsIssuer": "R10", "status": "200"}, "text": {"size": 21587, "hash": "d36af2488cfb260b310c23b4cee96d8ce6dbe971491db17576e3021a5c4a8f7c"}, "brand": [{"country": ["us"], "name": "Fake Shop", "vertical": ["Fashion"], "key": "fakeshop"}], "_id": "72f450ac-153d-472c-a280-642fd5787eed", "_score": null, "sort": [1719911981637, "72f450ac-153d-472c-a280-642fd5787eed"], "result": "https://urlscan.io/api/v1/result/72f450ac-153d-472c-a280-642fd5787eed/", "screenshot": "https://urlscan.io/screenshots/72f450ac-153d-472c-a280-642fd5787eed.png"}], "total": 488, "took": 36, "has_more": false}
