{"results": [{"verdicts": {"score": 0, "malicious": false, "urlscan": {"malicious": false}, "hasVerdicts": false}, "submitter": {"country": "us"}, "dom": {"size": 73653, "hash": "ed43bb5af09312959403b33beeaac0275b2f9080b45b140d6b3f1dd2667ef0c5"}, "frames": {"length": 4}, "canonical": {"task": {"url": "jazzaldia.eus"}, "page": {"url": "jazzaldia.eus"}}, "task": {"visibility": "unlisted", "method": "api", "domain": "jazzaldia.eus", "apexDomain": "jazzaldia.eus", "time": "2024-05-15T12:53:15.075Z", "uuid": "dd29ade4-01d1-40b8-9646-950617ede7ee", "url": "https://jazzaldia.eus/"}, "stats": {"uniqIPs": 12, "uniqCountries": 2, "dataLength": 13580580, "encodedDataLength": 11473340, "requests": 132}, "meta": [], "scanner": {"country": "us"}, "links": {"length": 21}, "page": {"country": "ES", "server": "Apache", "ip": "154.56.135.129", "mimeType": "text/html", "title": "59 Jazzaldia - Donostiako Jazzaldia", "url": "https://jazzaldia.eus/", "tlsValidDays": 89, "tlsAgeDays": 8, "ptr": "dns135129.phdns18.es", "tlsValidFrom": "2024-05-07T09:55:33.000Z", "domain": "jazzaldia.eus", "apexDomain": "jazzaldia.eus", "asnname": "PROFESIONALHOSTING, ES", "asn": "AS201446", "tlsIssuer": "R3", "status": "200"}, "text": {"size": 27966, "hash": "4d6924eb2ec7a08ec5422f77f28b0f89d3d5a7855708c610a0aae21a936091ce"}, "usertags": [], "_id": "dd29ade4-01d1-40b8-9646-950617ede7ee", "_score": null, "sort": [1715777595075, "dd29ade4-01d1-40b8-9646-950617ede7ee"], "result": "https://urlscan.io/api/v1/result/dd29ade4-01d1-40b8-9646-950617ede7ee/", "screenshot": "https://urlscan.io/screenshots/dd29ade4-01d1-40b8-9646-950617ede7ee.png"}], "total": 2, "took": 101, "has_more": false}
