{"results": [{"verdicts": {"score": 0, "malicious": false, "urlscan": {"malicious": false}, "hasVerdicts": false}, "submitter": {"country": "de"}, "dom": {"size": 352739, "hash": "65510547e8bde61b61f5a5a65bf2bd16ad469eee0f09ea42ae5e535d9a4660ca"}, "frames": {"length": 3}, "canonical": {"task": {"url": "friendship.com.vn"}, "page": {"url": "friendship.com.vn"}}, "labels": ["content.login"], "task": {"visibility": "public", "method": "api", "domain": "friendship.com.vn", "apexDomain": "friendship.com.vn", "time": "2024-04-26T08:22:42.250Z", "uuid": "093c4609-5bfa-4f49-a4bf-57a67a112a63", "url": "http://friendship.com.vn/", "tags": ["tranco_l324"]}, "stats": {"uniqIPs": 17, "uniqCountries": 3, "dataLength": 28312516, "encodedDataLength": 19273340, "requests": 189}, "meta": [], "scanner": {"country": "de"}, "links": {"length": 17}, "page": {"country": "VN", "server": "LiteSpeed", "redirected": "https-only", "ip": "103.82.23.11", "mimeType": "text/html", "title": "Friendship.com.vn - Winning Together", "url": "https://friendship.com.vn/", "tlsValidDays": 89, "tlsAgeDays": 50, "tlsValidFrom": "2024-03-06T19:19:49.000Z", "domain": "friendship.com.vn", "apexDomain": "friendship.com.vn", "asnname": "VNPT-AS-VN VIETNAM POSTS AND TELECOMMUNICATIONS GROUP, VN", "asn": "AS135905", "tlsIssuer": "R3", "status": "200"}, "text": {"size": 150701, "hash": "38e517f1aada041b7fdf6ece2aacce4e353dfd6ed3eb20257e444a75c7da530f"}, "usertags": [], "_id": "093c4609-5bfa-4f49-a4bf-57a67a112a63", "_score": null, "sort": [1714119762250, "093c4609-5bfa-4f49-a4bf-57a67a112a63"], "result": "https://urlscan.io/api/v1/result/093c4609-5bfa-4f49-a4bf-57a67a112a63/", "screenshot": "https://urlscan.io/screenshots/093c4609-5bfa-4f49-a4bf-57a67a112a63.png"}], "total": 23, "took": 44, "has_more": false}
