{"results": [{"verdicts": {"score": 0, "malicious": false, "urlscan": {"malicious": false}, "hasVerdicts": false}, "submitter": {"country": "fi"}, "dom": {"size": 32, "hash": "2185b4d357b8d48991767c140a5f4d0ad1207449a50856f8abe6b07f38a8b622"}, "frames": {"length": 1}, "canonical": {"task": {"url": "sns.io"}, "page": {"url": "sns.io"}}, "task": {"visibility": "public", "method": "api", "domain": "sns.io", "apexDomain": "sns.io", "time": "2024-02-21T21:46:33.921Z", "uuid": "43921520-b846-4cac-8a6f-31cac1508dce", "url": "http://sns.io/"}, "stats": {"uniqIPs": 1, "uniqCountries": 1, "dataLength": 6, "encodedDataLength": 233, "requests": 1}, "meta": [], "scanner": {"country": "fi"}, "links": {"length": 0}, "page": {"country": "US", "server": "nginx", "ip": "104.243.21.43", "domain": "sns.io", "apexDomain": "sns.io", "mimeType": "text/html", "asnname": "IT7NET, CA", "asn": "AS25820", "url": "http://sns.io/", "ptr": "104.243.21.43.16clouds.com", "status": "200"}, "text": {"size": 6, "hash": "1e8b2b6cab0a699041f7a3d19976478a6bd29a2e5aaeb99e233dbad13ff82521"}, "usertags": [], "_id": "43921520-b846-4cac-8a6f-31cac1508dce", "_score": null, "sort": [1708551993921, "43921520-b846-4cac-8a6f-31cac1508dce"], "result": "https://urlscan.io/api/v1/result/43921520-b846-4cac-8a6f-31cac1508dce/", "screenshot": "https://urlscan.io/screenshots/43921520-b846-4cac-8a6f-31cac1508dce.png"}], "total": 6, "took": 25, "has_more": false}
