{"results": [{"verdicts": {"score": 0, "malicious": false, "urlscan": {"malicious": false}, "hasVerdicts": false}, "submitter": {"country": "ca"}, "dom": {"size": 648200, "hash": "b84246fb4d569c1e5d71ad82f27c7d40ef4da7e2cbf4f36194a0c1d3eaee461b"}, "frames": {"length": 2}, "canonical": {"task": {"url": "trendtation.com"}, "page": {"url": "trendtation.com"}}, "task": {"visibility": "unlisted", "method": "manual", "domain": "trendtation.com", "apexDomain": "trendtation.com", "time": "2024-05-28T05:11:56.714Z", "uuid": "24c59469-5e92-4f60-8904-a5e4d46672d7", "url": "http://trendtation.com/"}, "stats": {"uniqIPs": 29, "uniqCountries": 3, "dataLength": 14971545, "encodedDataLength": 10836173, "requests": 110}, "meta": [], "scanner": {"country": "ca"}, "links": {"length": 100}, "page": {"country": "US", "server": "GSE", "redirected": "sub-domain", "ip": "142.251.163.121", "mimeType": "text/html", "title": "Trendtation", "url": "https://www.trendtation.com/", "tlsValidDays": 90, "tlsAgeDays": 7, "ptr": "wv-in-f121.1e100.net", "tlsValidFrom": "2024-05-20T14:28:45.000Z", "domain": "www.trendtation.com", "apexDomain": "trendtation.com", "asnname": "GOOGLE, US", "asn": "AS15169", "tlsIssuer": "WR3", "status": "200"}, "text": {"size": 416702, "hash": "300d55a46b39ce2072819a3d4fca473e096e7551a9063e0023ac9a394a47daac"}, "usertags": [], "_id": "24c59469-5e92-4f60-8904-a5e4d46672d7", "_score": null, "sort": [1716873116714, "24c59469-5e92-4f60-8904-a5e4d46672d7"], "result": "https://urlscan.io/api/v1/result/24c59469-5e92-4f60-8904-a5e4d46672d7/", "screenshot": "https://urlscan.io/screenshots/24c59469-5e92-4f60-8904-a5e4d46672d7.png"}], "total": 4, "took": 24, "has_more": false}
