{"results": [{"verdicts": {"score": 0, "malicious": false, "urlscan": {"malicious": false}, "hasVerdicts": false}, "submitter": {"country": "us"}, "task": {"visibility": "public", "method": "api", "domain": "balmoral-paris-hotel.com", "apexDomain": "balmoral-paris-hotel.com", "time": "2020-10-01T14:33:54.922Z", "uuid": "2213441b-f04f-406d-9cdd-6abe26f8d41b", "url": "http://balmoral-paris-hotel.com"}, "frames": {"length": 2}, "stats": {"uniqIPs": 21, "uniqCountries": 5, "dataLength": 8737718, "encodedDataLength": 7610685, "requests": 80}, "links": {"length": 9}, "canonical": {"task": {"url": "balmoral-paris-hotel.com"}, "page": {"url": "balmoral-paris-hotel.com"}}, "page": {"country": "US", "server": "AmazonS3", "redirected": "same-domain", "ip": "13.249.43.125", "mimeType": "text/html", "url": "https://balmoral-paris-hotel.com/", "tlsValidDays": 395, "tlsAgeDays": 98, "ptr": "server-13-249-43-125.iad89.r.cloudfront.net", "tlsValidFrom": "2020-06-25T00:00:00.000Z", "domain": "balmoral-paris-hotel.com", "apexDomain": "balmoral-paris-hotel.com", "asnname": "AMAZON-02, US", "asn": "AS16509", "tlsIssuer": "Amazon", "status": "200"}, "usertags": [], "meta": [], "_id": "2213441b-f04f-406d-9cdd-6abe26f8d41b", "_score": null, "sort": [1601562834922, "2213441b-f04f-406d-9cdd-6abe26f8d41b"], "result": "https://urlscan.io/api/v1/result/2213441b-f04f-406d-9cdd-6abe26f8d41b/", "screenshot": "https://urlscan.io/screenshots/2213441b-f04f-406d-9cdd-6abe26f8d41b.png"}], "total": 1, "took": 71, "has_more": false}
