{"results": [{"verdicts": {"score": 0, "malicious": false, "urlscan": {"malicious": false}, "hasVerdicts": false}, "submitter": {"country": "us"}, "dom": {"size": 171220, "hash": "a8d107272269abe07715e3a42823af5e468e89d0b8c7b3cda0d2658b4da384a5"}, "frames": {"length": 1}, "canonical": {"task": {"url": "uberdata.pgmfi.org"}, "page": {"url": "uberdata.pgmfi.org"}}, "task": {"visibility": "public", "method": "api", "domain": "uberdata.pgmfi.org", "apexDomain": "pgmfi.org", "time": "2024-03-26T14:26:52.048Z", "uuid": "fbaaf901-cdb2-4387-a8c0-c038d2d8af88", "url": "https://uberdata.pgmfi.org/"}, "stats": {"uniqIPs": 9, "uniqCountries": 2, "dataLength": 3026235, "encodedDataLength": 1074890, "requests": 32}, "meta": [], "scanner": {"country": "us"}, "links": {"length": 20}, "page": {"country": "HU", "server": "imunify360-webshield/1.21", "ip": "217.13.97.100", "mimeType": "text/html", "title": "Magyar Temetkez\u00e9s | Magyar temetkez\u00e9s - szakmai kiadv\u00e1ny ", "url": "https://uberdata.pgmfi.org/", "tlsValidDays": 89, "tlsAgeDays": 22, "ptr": "hu5.teratarhely.hu", "tlsValidFrom": "2024-03-04T01:43:22.000Z", "domain": "uberdata.pgmfi.org", "apexDomain": "pgmfi.org", "asnname": "RENDSZERNET-AS, HU", "asn": "AS60071", "tlsIssuer": "R3", "status": "200"}, "text": {"size": 138446, "hash": "9f1c18eec0f450e3f88a602e90f4d4e4496e595d9a71967b513cb66e99f6ac22"}, "usertags": [], "_id": "fbaaf901-cdb2-4387-a8c0-c038d2d8af88", "_score": null, "sort": [1711463212048, "fbaaf901-cdb2-4387-a8c0-c038d2d8af88"], "result": "https://urlscan.io/api/v1/result/fbaaf901-cdb2-4387-a8c0-c038d2d8af88/", "screenshot": "https://urlscan.io/screenshots/fbaaf901-cdb2-4387-a8c0-c038d2d8af88.png"}], "total": 3, "took": 26, "has_more": false}
