{"results": [{"source": {"page": "www.eigolink.net/site/hdpronetwork.com", "subdomain": "www.eigolink.net", "root_domain": "eigolink.net", "title": "hdpronetwork.com - HD Pro Guide Network - HD Pro Network", "last_crawled": "2022-07-14", "http_code": 200, "pages_to_page": 1, "nofollow_pages_to_page": 0, "redirect_pages_to_page": 0, "external_pages_to_page": 0, "external_nofollow_pages_to_page": 0, "external_redirect_pages_to_page": 0, "deleted_pages_to_page": 0, "root_domains_to_page": 0, "indirect_root_domains_to_page": 0, "deleted_root_domains_to_page": 0, "nofollow_root_domains_to_page": 0, "pages_to_subdomain": 86799528, "nofollow_pages_to_subdomain": 71973, "redirect_pages_to_subdomain": 103386, "external_pages_to_subdomain": 295250, "external_nofollow_pages_to_subdomain": 51651, "external_redirect_pages_to_subdomain": 103336, "deleted_pages_to_subdomain": 66856, "root_domains_to_subdomain": 3644, "deleted_root_domains_to_subdomain": 1432, "nofollow_root_domains_to_subdomain": 913, "pages_to_root_domain": 86799984, "nofollow_pages_to_root_domain": 72419, "redirect_pages_to_root_domain": 103386, "external_pages_to_root_domain": 295706, "external_indirect_pages_to_root_domain": 120381, "external_nofollow_pages_to_root_domain": 52097, "external_redirect_pages_to_root_domain": 103336, "deleted_pages_to_root_domain": 67955, "root_domains_to_root_domain": 3648, "indirect_root_domains_to_root_domain": 51, "deleted_root_domains_to_root_domain": 1432, "nofollow_root_domains_to_root_domain": 914, "page_authority": 28, "domain_authority": 27, "link_propensity": 0.5870283842, "spam_score": 59, "root_domains_from_page": 9, "nofollow_root_domains_from_page": 9, "pages_from_page": 9, "nofollow_pages_from_page": 9, "root_domains_from_root_domain": 1784025, "nofollow_root_domains_from_root_domain": 1784019, "pages_from_root_domain": 12530103, "nofollow_pages_from_root_domain": 12530080, "pages_crawled_from_root_domain": 3039078}, "target": {"page": "itpronetwork.net/", "subdomain": "itpronetwork.net", "root_domain": "itpronetwork.net", "title": "", "last_crawled": "2024-04-24", "http_code": 200, "pages_to_page": 3, "nofollow_pages_to_page": 2, "redirect_pages_to_page": 0, "external_pages_to_page": 3, "external_nofollow_pages_to_page": 2, "external_redirect_pages_to_page": 0, "deleted_pages_to_page": 2, "root_domains_to_page": 3, "indirect_root_domains_to_page": 0, "deleted_root_domains_to_page": 1, "nofollow_root_domains_to_page": 2, "pages_to_subdomain": 3, "nofollow_pages_to_subdomain": 2, "redirect_pages_to_subdomain": 0, "external_pages_to_subdomain": 3, "external_nofollow_pages_to_subdomain": 2, "external_redirect_pages_to_subdomain": 0, "deleted_pages_to_subdomain": 4, "root_domains_to_subdomain": 3, "deleted_root_domains_to_subdomain": 1, "nofollow_root_domains_to_subdomain": 2, "pages_to_root_domain": 3, "nofollow_pages_to_root_domain": 2, "redirect_pages_to_root_domain": 0, "external_pages_to_root_domain": 3, "external_indirect_pages_to_root_domain": 0, "external_nofollow_pages_to_root_domain": 2, "external_redirect_pages_to_root_domain": 0, "deleted_pages_to_root_domain": 4, "root_domains_to_root_domain": 3, "indirect_root_domains_to_root_domain": 0, "deleted_root_domains_to_root_domain": 1, "nofollow_root_domains_to_root_domain": 2, "page_authority": 10, "domain_authority": 1, "link_propensity": 0, "spam_score": 48, "root_domains_from_page": 0, "nofollow_root_domains_from_page": 0, "pages_from_page": 0, "nofollow_pages_from_page": 0, "root_domains_from_root_domain": 0, "nofollow_root_domains_from_root_domain": 0, "pages_from_root_domain": 0, "nofollow_pages_from_root_domain": 0, "pages_crawled_from_root_domain": 5}, "anchor_text": "", "date_first_seen": "2022-07-14", "date_last_seen": "2022-07-14", "date_disappeared": "", "nofollow": true, "redirect": false, "rel_canonical": false, "via_redirect": false, "via_rel_canonical": false}], "next_token": "Acj+LBVjr2YU"}
